SLRIC/__init__.py
SLRIC/slric.py
SLRIC/classes/GraphQW.py
SLRIC/classes/__init__.py
SLRIC/methods/__init__.py
SLRIC/methods/direct_influence.py
SLRIC/methods/indirect_influence.py
SLRIC/methods/lric.py
SLRIC/methods/netsim.py
SLRIC/methods/sric.py
slric-1.1.6.dist-info/licenses/LICENSE.txt
slric-1.1.6.dist-info/METADATA
slric-1.1.6.dist-info/WHEEL
slric-1.1.6.dist-info/top_level.txt
slric-1.1.6.dist-info/RECORD
