Metadata-Version: 2.4
Name: slric
Version: 1.1.6
Summary: SRIC and LRIC indices calculation
Home-page: https://github.com/SergSHV/slric
Author: Fuad Aleskerov, Natalia Meshcheryahkova, Sergey Shvydun(*)
Author-email: shvydun@hse.ru
License: BSD 3-clause "New" or "Revised License"
License-File: LICENSE.txt
Requires-Dist: numpy
Requires-Dist: cvxopt
Requires-Dist: networkx>=2.3
Dynamic: author
Dynamic: author-email
Dynamic: description
Dynamic: description-content-type
Dynamic: home-page
Dynamic: license
Dynamic: license-file
Dynamic: requires-dist
Dynamic: summary
